s3path/__init__.py
s3path/accessor.py
s3path/current_version.py
s3path/old_versions.py
s3path/py.typed
s3path-0.6.5.dist-info/licenses/LICENSE
s3path-0.6.5.dist-info/METADATA
s3path-0.6.5.dist-info/WHEEL
s3path-0.6.5.dist-info/top_level.txt
s3path-0.6.5.dist-info/RECORD
